<MutexBB>
<BB1 name="for.body7.us.us_0_0">
	<BB2 name="for.body7.us.us_0_1"/>
</BB1>
<BB1 name="for.body7.us.us_0_1">
	<BB2 name="for.body7.us.us_0_0"/>
</BB1>
</MutexBB>
<DFG count="99">
<Node idx="11"ASAP="0"BB="for.body7.us.us"CONST="-1">
<OP>OLOAD</OP>
<Inputs>
</Inputs>
<Outputs>
	<Output idx="10" type="I2"/>
	<Output idx="22" type="I2"/>
	<Output idx="32" type="I2"/>
	<Output idx="42" type="I2"/>
	<Output idx="52" type="I2"/>
	<Output idx="62" type="I2"/>
	<Output idx="72" type="I2"/>
	<Output idx="81" type="I2"/>
</Outputs>
<RecParents>
</RecParents>
</Node>

<Node idx="0"ASAP="0"BB="for.body7.us.us">
<OP>SELECT</OP>
<Inputs>
	<Input idx="91"/>
	<Input idx="89"/>
</Inputs>
<Outputs>
	<Output idx="1" type="I1"/>
	<Output idx="3" type="I1"/>
	<Output idx="16" type="I1"/>
	<Output idx="26" type="I1"/>
	<Output idx="36" type="I1"/>
	<Output idx="46" type="I1"/>
	<Output idx="56" type="I1"/>
	<Output idx="66" type="I1"/>
	<Output idx="76" type="I1"/>
	<Output idx="81" type="I1"/>
</Outputs>
<RecParents>
</RecParents>
</Node>

<Node idx="5"ASAP="1"BB="for.body7.us.us"CONST="-1">
<OP>OLOAD</OP>
<Inputs>
</Inputs>
<Outputs>
	<Output idx="4" type="I2"/>
	<Output idx="17" type="I2"/>
	<Output idx="27" type="I2"/>
	<Output idx="37" type="I2"/>
	<Output idx="47" type="I2"/>
	<Output idx="57" type="I2"/>
	<Output idx="67" type="I2"/>
	<Output idx="76" type="I2"/>
</Outputs>
<RecParents>
</RecParents>
</Node>

<Node idx="3"ASAP="1"BB="for.body7.us.us"CONST="7">
<OP>OR</OP>
<Inputs>
	<Input idx="0"/>
</Inputs>
<Outputs>
	<Output idx="4" type="I1"/>
	<Output idx="10" type="I1"/>
</Outputs>
<RecParents>
</RecParents>
</Node>

<Node idx="85"ASAP="1"BB="for.body7.us.us">
<OP>SELECT</OP>
<Inputs>
	<Input idx="90"/>
	<Input idx="94"/>
</Inputs>
<Outputs>
	<Output idx="86" type="I1"/>
</Outputs>
<RecParents>
</RecParents>
</Node>

<Node idx="16"ASAP="1"BB="for.body7.us.us"CONST="6">
<OP>OR</OP>
<Inputs>
	<Input idx="0"/>
</Inputs>
<Outputs>
	<Output idx="17" type="I1"/>
	<Output idx="22" type="I1"/>
</Outputs>
<RecParents>
</RecParents>
</Node>

<Node idx="81"ASAP="1"BB="for.body7.us.us">
<OP>ADD</OP>
<Inputs>
	<Input idx="11"/>
	<Input idx="0"/>
</Inputs>
<Outputs>
	<Output idx="82" type="I1"/>
</Outputs>
<RecParents>
</RecParents>
</Node>

<Node idx="26"ASAP="1"BB="for.body7.us.us"CONST="5">
<OP>OR</OP>
<Inputs>
	<Input idx="0"/>
</Inputs>
<Outputs>
	<Output idx="27" type="I1"/>
	<Output idx="32" type="I1"/>
</Outputs>
<RecParents>
</RecParents>
</Node>

<Node idx="66"ASAP="1"BB="for.body7.us.us"CONST="1">
<OP>OR</OP>
<Inputs>
	<Input idx="0"/>
</Inputs>
<Outputs>
	<Output idx="67" type="I1"/>
	<Output idx="72" type="I1"/>
</Outputs>
<RecParents>
</RecParents>
</Node>

<Node idx="36"ASAP="1"BB="for.body7.us.us"CONST="4">
<OP>OR</OP>
<Inputs>
	<Input idx="0"/>
</Inputs>
<Outputs>
	<Output idx="37" type="I1"/>
	<Output idx="42" type="I1"/>
</Outputs>
<RecParents>
</RecParents>
</Node>

<Node idx="56"ASAP="1"BB="for.body7.us.us"CONST="2">
<OP>OR</OP>
<Inputs>
	<Input idx="0"/>
</Inputs>
<Outputs>
	<Output idx="57" type="I1"/>
	<Output idx="62" type="I1"/>
</Outputs>
<RecParents>
</RecParents>
</Node>

<Node idx="46"ASAP="1"BB="for.body7.us.us"CONST="3">
<OP>OR</OP>
<Inputs>
	<Input idx="0"/>
</Inputs>
<Outputs>
	<Output idx="47" type="I1"/>
	<Output idx="52" type="I1"/>
</Outputs>
<RecParents>
</RecParents>
</Node>

<Node idx="67"ASAP="2"BB="for.body7.us.us">
<OP>ADD</OP>
<Inputs>
	<Input idx="5"/>
	<Input idx="66"/>
</Inputs>
<Outputs>
	<Output idx="68" type="I1"/>
</Outputs>
<RecParents>
</RecParents>
</Node>

<Node idx="15"ASAP="2"BB="for.body7.us.us"CONST="-1">
<OP>OLOAD</OP>
<Inputs>
</Inputs>
<Outputs>
	<Output idx="14" type="I1"/>
	<Output idx="25" type="I1"/>
	<Output idx="35" type="I1"/>
	<Output idx="45" type="I1"/>
	<Output idx="55" type="I1"/>
	<Output idx="65" type="I1"/>
	<Output idx="75" type="I1"/>
	<Output idx="84" type="I1"/>
</Outputs>
<RecParents>
</RecParents>
</Node>

<Node idx="17"ASAP="2"BB="for.body7.us.us">
<OP>ADD</OP>
<Inputs>
	<Input idx="5"/>
	<Input idx="16"/>
</Inputs>
<Outputs>
	<Output idx="18" type="I1"/>
</Outputs>
<RecParents>
</RecParents>
</Node>

<Node idx="86"ASAP="2"BB="for.body7.us.us"CONST="-8">
<OP>ADD</OP>
<Inputs>
	<Input idx="85"/>
</Inputs>
<Outputs>
	<Output idx="87" type="I1"/>
	<Output idx="90" type="I1"/>
</Outputs>
<RecParents>
</RecParents>
</Node>

<Node idx="82"ASAP="2"BB="for.body7.us.us"CONST="-1">
<OP>ADD</OP>
<Inputs>
	<Input idx="81"/>
</Inputs>
<Outputs>
	<Output idx="83" type="I2"/>
</Outputs>
<RecParents>
</RecParents>
</Node>

<Node idx="10"ASAP="2"BB="for.body7.us.us">
<OP>ADD</OP>
<Inputs>
	<Input idx="11"/>
	<Input idx="3"/>
</Inputs>
<Outputs>
	<Output idx="12" type="I1"/>
</Outputs>
<RecParents>
</RecParents>
</Node>

<Node idx="22"ASAP="2"BB="for.body7.us.us">
<OP>ADD</OP>
<Inputs>
	<Input idx="11"/>
	<Input idx="16"/>
</Inputs>
<Outputs>
	<Output idx="23" type="I1"/>
</Outputs>
<RecParents>
</RecParents>
</Node>

<Node idx="76"ASAP="2"BB="for.body7.us.us">
<OP>ADD</OP>
<Inputs>
	<Input idx="5"/>
	<Input idx="0"/>
</Inputs>
<Outputs>
	<Output idx="77" type="I1"/>
</Outputs>
<RecParents>
</RecParents>
</Node>

<Node idx="72"ASAP="2"BB="for.body7.us.us">
<OP>ADD</OP>
<Inputs>
	<Input idx="11"/>
	<Input idx="66"/>
</Inputs>
<Outputs>
	<Output idx="73" type="I1"/>
</Outputs>
<RecParents>
</RecParents>
</Node>

<Node idx="27"ASAP="2"BB="for.body7.us.us">
<OP>ADD</OP>
<Inputs>
	<Input idx="5"/>
	<Input idx="26"/>
</Inputs>
<Outputs>
	<Output idx="28" type="I1"/>
</Outputs>
<RecParents>
</RecParents>
</Node>

<Node idx="4"ASAP="2"BB="for.body7.us.us">
<OP>ADD</OP>
<Inputs>
	<Input idx="5"/>
	<Input idx="3"/>
</Inputs>
<Outputs>
	<Output idx="6" type="I1"/>
</Outputs>
<RecParents>
</RecParents>
</Node>

<Node idx="32"ASAP="2"BB="for.body7.us.us">
<OP>ADD</OP>
<Inputs>
	<Input idx="11"/>
	<Input idx="26"/>
</Inputs>
<Outputs>
	<Output idx="33" type="I1"/>
</Outputs>
<RecParents>
</RecParents>
</Node>

<Node idx="62"ASAP="2"BB="for.body7.us.us">
<OP>ADD</OP>
<Inputs>
	<Input idx="11"/>
	<Input idx="56"/>
</Inputs>
<Outputs>
	<Output idx="63" type="I1"/>
</Outputs>
<RecParents>
</RecParents>
</Node>

<Node idx="57"ASAP="2"BB="for.body7.us.us">
<OP>ADD</OP>
<Inputs>
	<Input idx="5"/>
	<Input idx="56"/>
</Inputs>
<Outputs>
	<Output idx="58" type="I1"/>
</Outputs>
<RecParents>
</RecParents>
</Node>

<Node idx="37"ASAP="2"BB="for.body7.us.us">
<OP>ADD</OP>
<Inputs>
	<Input idx="5"/>
	<Input idx="36"/>
</Inputs>
<Outputs>
	<Output idx="38" type="I1"/>
</Outputs>
<RecParents>
</RecParents>
</Node>

<Node idx="52"ASAP="2"BB="for.body7.us.us">
<OP>ADD</OP>
<Inputs>
	<Input idx="11"/>
	<Input idx="46"/>
</Inputs>
<Outputs>
	<Output idx="53" type="I1"/>
</Outputs>
<RecParents>
</RecParents>
</Node>

<Node idx="42"ASAP="2"BB="for.body7.us.us">
<OP>ADD</OP>
<Inputs>
	<Input idx="11"/>
	<Input idx="36"/>
</Inputs>
<Outputs>
	<Output idx="43" type="I1"/>
</Outputs>
<RecParents>
</RecParents>
</Node>

<Node idx="47"ASAP="2"BB="for.body7.us.us">
<OP>ADD</OP>
<Inputs>
	<Input idx="5"/>
	<Input idx="46"/>
</Inputs>
<Outputs>
	<Output idx="48" type="I1"/>
</Outputs>
<RecParents>
</RecParents>
</Node>

<Node idx="92"ASAP="2"BB="for.body7.us.us"CONST="4094">
<OP>LOADB</OP>
<Inputs>
</Inputs>
<Outputs>
	<Output idx="95" type="I1"/>
	<Output idx="96" type="I1"/>
</Outputs>
<RecParents>
</RecParents>
</Node>

<Node idx="96"ASAP="3"BB="for.body7.us.us"CONST="-2">
<OP>AND</OP>
<Inputs>
	<Input idx="92"/>
</Inputs>
<Outputs>
	<Output idx="97" type="P"/>
</Outputs>
<RecParents>
</RecParents>
</Node>

<Node idx="18"ASAP="3"BB="for.body7.us.us"CONST="-1">
<OP>ADD</OP>
<Inputs>
	<Input idx="17"/>
</Inputs>
<Outputs>
	<Output idx="19" type="I2"/>
	<Output idx="20" type="I2"/>
</Outputs>
<RecParents>
</RecParents>
</Node>

<Node idx="68"ASAP="3"BB="for.body7.us.us"CONST="-1">
<OP>ADD</OP>
<Inputs>
	<Input idx="67"/>
</Inputs>
<Outputs>
	<Output idx="69" type="I2"/>
	<Output idx="70" type="I2"/>
</Outputs>
<RecParents>
</RecParents>
</Node>

<Node idx="77"ASAP="3"BB="for.body7.us.us"CONST="-1">
<OP>ADD</OP>
<Inputs>
	<Input idx="76"/>
</Inputs>
<Outputs>
	<Output idx="78" type="I2"/>
	<Output idx="79" type="I2"/>
</Outputs>
<RecParents>
</RecParents>
</Node>

<Node idx="38"ASAP="3"BB="for.body7.us.us"CONST="-1">
<OP>ADD</OP>
<Inputs>
	<Input idx="37"/>
</Inputs>
<Outputs>
	<Output idx="39" type="I2"/>
	<Output idx="40" type="I2"/>
</Outputs>
<RecParents>
</RecParents>
</Node>

<Node idx="28"ASAP="3"BB="for.body7.us.us"CONST="-1">
<OP>ADD</OP>
<Inputs>
	<Input idx="27"/>
</Inputs>
<Outputs>
	<Output idx="29" type="I2"/>
	<Output idx="30" type="I2"/>
</Outputs>
<RecParents>
</RecParents>
</Node>

<Node idx="33"ASAP="3"BB="for.body7.us.us"CONST="-1">
<OP>ADD</OP>
<Inputs>
	<Input idx="32"/>
</Inputs>
<Outputs>
	<Output idx="34" type="I2"/>
</Outputs>
<RecParents>
</RecParents>
</Node>

<Node idx="23"ASAP="3"BB="for.body7.us.us"CONST="-1">
<OP>ADD</OP>
<Inputs>
	<Input idx="22"/>
</Inputs>
<Outputs>
	<Output idx="24" type="I2"/>
</Outputs>
<RecParents>
</RecParents>
</Node>

<Node idx="12"ASAP="3"BB="for.body7.us.us"CONST="-1">
<OP>ADD</OP>
<Inputs>
	<Input idx="10"/>
</Inputs>
<Outputs>
	<Output idx="13" type="I2"/>
</Outputs>
<RecParents>
</RecParents>
</Node>

<Node idx="6"ASAP="3"BB="for.body7.us.us"CONST="-1">
<OP>ADD</OP>
<Inputs>
	<Input idx="4"/>
</Inputs>
<Outputs>
	<Output idx="7" type="I2"/>
	<Output idx="8" type="I2"/>
</Outputs>
<RecParents>
</RecParents>
</Node>

<Node idx="43"ASAP="3"BB="for.body7.us.us"CONST="-1">
<OP>ADD</OP>
<Inputs>
	<Input idx="42"/>
</Inputs>
<Outputs>
	<Output idx="44" type="I2"/>
</Outputs>
<RecParents>
</RecParents>
</Node>

<Node idx="83"ASAP="3"BB="for.body7.us.us">
<OP>LOAD</OP>
<Inputs>
	<Input idx="82"/>
</Inputs>
<Outputs>
	<Output idx="84" type="I2"/>
</Outputs>
<RecParents>
</RecParents>
</Node>

<Node idx="63"ASAP="3"BB="for.body7.us.us"CONST="-1">
<OP>ADD</OP>
<Inputs>
	<Input idx="62"/>
</Inputs>
<Outputs>
	<Output idx="64" type="I2"/>
</Outputs>
<RecParents>
</RecParents>
</Node>

<Node idx="1"ASAP="3"BB="for.body7.us.us"CONST="8">
<OP>ADD</OP>
<Inputs>
	<Input idx="0"/>
</Inputs>
<Outputs>
	<Output idx="2" type="I1"/>
	<Output idx="89" type="I1"/>
</Outputs>
<RecParents>
</RecParents>
</Node>

<Node idx="73"ASAP="3"BB="for.body7.us.us"CONST="-1">
<OP>ADD</OP>
<Inputs>
	<Input idx="72"/>
</Inputs>
<Outputs>
	<Output idx="74" type="I2"/>
</Outputs>
<RecParents>
</RecParents>
</Node>

<Node idx="87"ASAP="3"BB="for.body7.us.us"CONST="0">
<OP>CMP</OP>
<Inputs>
	<Input idx="86"/>
</Inputs>
<Outputs>
	<Output idx="88" type="I1"/>
</Outputs>
<RecParents>
</RecParents>
</Node>

<Node idx="48"ASAP="3"BB="for.body7.us.us"CONST="-1">
<OP>ADD</OP>
<Inputs>
	<Input idx="47"/>
</Inputs>
<Outputs>
	<Output idx="49" type="I2"/>
	<Output idx="50" type="I2"/>
</Outputs>
<RecParents>
</RecParents>
</Node>

<Node idx="53"ASAP="3"BB="for.body7.us.us"CONST="-1">
<OP>ADD</OP>
<Inputs>
	<Input idx="52"/>
</Inputs>
<Outputs>
	<Output idx="54" type="I2"/>
</Outputs>
<RecParents>
</RecParents>
</Node>

<Node idx="99"ASAP="3"BB="for.body7.us.us"CONST="16384">
<OP>MOVC</OP>
<Inputs>
</Inputs>
<Outputs>
	<Output idx="98" type="I1"/>
</Outputs>
<RecParents>
</RecParents>
</Node>

<Node idx="94"ASAP="3"BB="for.body7.us.us"CONST="-1">
<OP>OLOAD</OP>
<Inputs>
	<Input idx="95"/>
</Inputs>
<Outputs>
	<Output idx="85" type="I1"/>
</Outputs>
<RecParents>
</RecParents>
</Node>

<Node idx="95"ASAP="3"BB="for.body7.us.us"CONST="1">
<OP>AND</OP>
<Inputs>
	<Input idx="92"/>
</Inputs>
<Outputs>
	<Output idx="91" type="P"/>
	<Output idx="94" type="P"/>
</Outputs>
<RecParents>
</RecParents>
</Node>

<Node idx="58"ASAP="3"BB="for.body7.us.us"CONST="-1">
<OP>ADD</OP>
<Inputs>
	<Input idx="57"/>
</Inputs>
<Outputs>
	<Output idx="59" type="I2"/>
	<Output idx="60" type="I2"/>
</Outputs>
<RecParents>
</RecParents>
</Node>

<Node idx="64"ASAP="4"BB="for.body7.us.us">
<OP>LOAD</OP>
<Inputs>
	<Input idx="63"/>
</Inputs>
<Outputs>
	<Output idx="65" type="I2"/>
</Outputs>
<RecParents>
</RecParents>
</Node>

<Node idx="60"ASAP="4"BB="for.body7.us.us">
<OP>LOAD</OP>
<Inputs>
	<Input idx="58"/>
</Inputs>
<Outputs>
	<Output idx="61" type="I1"/>
</Outputs>
<RecParents>
</RecParents>
</Node>

<Node idx="34"ASAP="4"BB="for.body7.us.us">
<OP>LOAD</OP>
<Inputs>
	<Input idx="33"/>
</Inputs>
<Outputs>
	<Output idx="35" type="I2"/>
</Outputs>
<RecParents>
</RecParents>
</Node>

<Node idx="54"ASAP="4"BB="for.body7.us.us">
<OP>LOAD</OP>
<Inputs>
	<Input idx="53"/>
</Inputs>
<Outputs>
	<Output idx="55" type="I2"/>
</Outputs>
<RecParents>
</RecParents>
</Node>

<Node idx="40"ASAP="4"BB="for.body7.us.us">
<OP>LOAD</OP>
<Inputs>
	<Input idx="38"/>
</Inputs>
<Outputs>
	<Output idx="41" type="I1"/>
</Outputs>
<RecParents>
</RecParents>
</Node>

<Node idx="50"ASAP="4"BB="for.body7.us.us">
<OP>LOAD</OP>
<Inputs>
	<Input idx="48"/>
</Inputs>
<Outputs>
	<Output idx="51" type="I1"/>
</Outputs>
<RecParents>
</RecParents>
</Node>

<Node idx="30"ASAP="4"BB="for.body7.us.us">
<OP>LOAD</OP>
<Inputs>
	<Input idx="28"/>
</Inputs>
<Outputs>
	<Output idx="31" type="I1"/>
</Outputs>
<RecParents>
</RecParents>
</Node>

<Node idx="2"ASAP="4"BB="for.body7.us.us"CONST="-1">
<OP>OSTORE</OP>
<Inputs>
	<Input idx="1"/>
</Inputs>
<Outputs>
</Outputs>
<RecParents>
</RecParents>
</Node>

<Node idx="70"ASAP="4"BB="for.body7.us.us">
<OP>LOAD</OP>
<Inputs>
	<Input idx="68"/>
</Inputs>
<Outputs>
	<Output idx="71" type="I1"/>
</Outputs>
<RecParents>
</RecParents>
</Node>

<Node idx="24"ASAP="4"BB="for.body7.us.us">
<OP>LOAD</OP>
<Inputs>
	<Input idx="23"/>
</Inputs>
<Outputs>
	<Output idx="25" type="I2"/>
</Outputs>
<RecParents>
</RecParents>
</Node>

<Node idx="97"ASAP="4"BB="for.body7.us.us"CONST="4094">
<OP>STOREB</OP>
<Inputs>
	<Input idx="96"/>
</Inputs>
<Outputs>
</Outputs>
<RecParents>
</RecParents>
</Node>

<Node idx="79"ASAP="4"BB="for.body7.us.us">
<OP>LOAD</OP>
<Inputs>
	<Input idx="77"/>
</Inputs>
<Outputs>
	<Output idx="80" type="I1"/>
</Outputs>
<RecParents>
</RecParents>
</Node>

<Node idx="20"ASAP="4"BB="for.body7.us.us">
<OP>LOAD</OP>
<Inputs>
	<Input idx="18"/>
</Inputs>
<Outputs>
	<Output idx="21" type="I1"/>
</Outputs>
<RecParents>
</RecParents>
</Node>

<Node idx="84"ASAP="4"BB="for.body7.us.us">
<OP>MUL</OP>
<Inputs>
	<Input idx="15"/>
	<Input idx="83"/>
</Inputs>
<Outputs>
	<Output idx="80" type="I2"/>
</Outputs>
<RecParents>
</RecParents>
</Node>

<Node idx="44"ASAP="4"BB="for.body7.us.us">
<OP>LOAD</OP>
<Inputs>
	<Input idx="43"/>
</Inputs>
<Outputs>
	<Output idx="45" type="I2"/>
</Outputs>
<RecParents>
</RecParents>
</Node>

<Node idx="13"ASAP="4"BB="for.body7.us.us">
<OP>LOAD</OP>
<Inputs>
	<Input idx="12"/>
</Inputs>
<Outputs>
	<Output idx="14" type="I2"/>
</Outputs>
<RecParents>
</RecParents>
</Node>

<Node idx="8"ASAP="4"BB="for.body7.us.us">
<OP>LOAD</OP>
<Inputs>
	<Input idx="6"/>
</Inputs>
<Outputs>
	<Output idx="9" type="I1"/>
</Outputs>
<RecParents>
</RecParents>
</Node>

<Node idx="88"ASAP="4"BB="for.body7.us.us"CONST="0">
<OP>OR</OP>
<Inputs>
	<Input idx="87"/>
</Inputs>
<Outputs>
	<Output idx="89" type="P"/>
	<Output idx="90" type="P"/>
	<Output idx="98" type="P"/>
</Outputs>
<RecParents>
</RecParents>
</Node>

<Node idx="91"ASAP="4"BB="for.body7.us.us_0_0"CONST="0">
<OP>CMERGE</OP>
<Inputs>
	<Input idx="95"/>
</Inputs>
<Outputs>
	<Output idx="0" type="I1"/>
</Outputs>
<RecParents>
</RecParents>
</Node>

<Node idx="74"ASAP="4"BB="for.body7.us.us">
<OP>LOAD</OP>
<Inputs>
	<Input idx="73"/>
</Inputs>
<Outputs>
	<Output idx="75" type="I2"/>
</Outputs>
<RecParents>
</RecParents>
</Node>

<Node idx="75"ASAP="5"BB="for.body7.us.us">
<OP>MUL</OP>
<Inputs>
	<Input idx="15"/>
	<Input idx="74"/>
</Inputs>
<Outputs>
	<Output idx="71" type="I2"/>
</Outputs>
<RecParents>
</RecParents>
</Node>

<Node idx="25"ASAP="5"BB="for.body7.us.us">
<OP>MUL</OP>
<Inputs>
	<Input idx="15"/>
	<Input idx="24"/>
</Inputs>
<Outputs>
	<Output idx="21" type="I2"/>
</Outputs>
<RecParents>
</RecParents>
</Node>

<Node idx="80"ASAP="5"BB="for.body7.us.us">
<OP>ADD</OP>
<Inputs>
	<Input idx="79"/>
	<Input idx="84"/>
</Inputs>
<Outputs>
	<Output idx="78" type="I1"/>
</Outputs>
<RecParents>
</RecParents>
</Node>

<Node idx="35"ASAP="5"BB="for.body7.us.us">
<OP>MUL</OP>
<Inputs>
	<Input idx="15"/>
	<Input idx="34"/>
</Inputs>
<Outputs>
	<Output idx="31" type="I2"/>
</Outputs>
<RecParents>
</RecParents>
</Node>

<Node idx="14"ASAP="5"BB="for.body7.us.us">
<OP>MUL</OP>
<Inputs>
	<Input idx="15"/>
	<Input idx="13"/>
</Inputs>
<Outputs>
	<Output idx="9" type="I2"/>
</Outputs>
<RecParents>
</RecParents>
</Node>

<Node idx="89"ASAP="5"BB="for.body7.us.us_0_1">
<OP>CMERGE</OP>
<Inputs>
	<Input idx="88"/>
	<Input idx="1"/>
</Inputs>
<Outputs>
	<Output idx="0" type="I2"/>
</Outputs>
<RecParents>
</RecParents>
</Node>

<Node idx="90"ASAP="5"BB="for.body7.us.us_85_0">
<OP>CMERGE</OP>
<Inputs>
	<Input idx="88"/>
	<Input idx="86"/>
</Inputs>
<Outputs>
	<Output idx="85" type="I2"/>
</Outputs>
<RecParents>
</RecParents>
</Node>

<Node idx="98"ASAP="5"BB="for.cond5.for.end_crit_edge.us.us.unr-lcssa.loopexit"CONST="2047">
<OP>STOREB</OP>
<Inputs>
	<Input idx="88"/>
	<Input idx="99"/>
</Inputs>
<Outputs>
</Outputs>
<RecParents>
</RecParents>
</Node>

<Node idx="45"ASAP="5"BB="for.body7.us.us">
<OP>MUL</OP>
<Inputs>
	<Input idx="15"/>
	<Input idx="44"/>
</Inputs>
<Outputs>
	<Output idx="41" type="I2"/>
</Outputs>
<RecParents>
</RecParents>
</Node>

<Node idx="55"ASAP="5"BB="for.body7.us.us">
<OP>MUL</OP>
<Inputs>
	<Input idx="15"/>
	<Input idx="54"/>
</Inputs>
<Outputs>
	<Output idx="51" type="I2"/>
</Outputs>
<RecParents>
</RecParents>
</Node>

<Node idx="65"ASAP="5"BB="for.body7.us.us">
<OP>MUL</OP>
<Inputs>
	<Input idx="15"/>
	<Input idx="64"/>
</Inputs>
<Outputs>
	<Output idx="61" type="I2"/>
</Outputs>
<RecParents>
</RecParents>
</Node>

<Node idx="9"ASAP="6"BB="for.body7.us.us">
<OP>ADD</OP>
<Inputs>
	<Input idx="8"/>
	<Input idx="14"/>
</Inputs>
<Outputs>
	<Output idx="7" type="I1"/>
</Outputs>
<RecParents>
</RecParents>
</Node>

<Node idx="78"ASAP="6"BB="for.body7.us.us">
<OP>STORE</OP>
<Inputs>
	<Input idx="77"/>
	<Input idx="80"/>
</Inputs>
<Outputs>
</Outputs>
<RecParents>
	<RecParent idx="8"/>
	<RecParent idx="13"/>
	<RecParent idx="20"/>
	<RecParent idx="24"/>
	<RecParent idx="30"/>
	<RecParent idx="34"/>
	<RecParent idx="40"/>
	<RecParent idx="44"/>
	<RecParent idx="50"/>
	<RecParent idx="54"/>
	<RecParent idx="60"/>
	<RecParent idx="64"/>
	<RecParent idx="70"/>
	<RecParent idx="74"/>
</RecParents>
</Node>

<Node idx="21"ASAP="6"BB="for.body7.us.us">
<OP>ADD</OP>
<Inputs>
	<Input idx="20"/>
	<Input idx="25"/>
</Inputs>
<Outputs>
	<Output idx="19" type="I1"/>
</Outputs>
<RecParents>
</RecParents>
</Node>

<Node idx="61"ASAP="6"BB="for.body7.us.us">
<OP>ADD</OP>
<Inputs>
	<Input idx="60"/>
	<Input idx="65"/>
</Inputs>
<Outputs>
	<Output idx="59" type="I1"/>
</Outputs>
<RecParents>
</RecParents>
</Node>

<Node idx="51"ASAP="6"BB="for.body7.us.us">
<OP>ADD</OP>
<Inputs>
	<Input idx="50"/>
	<Input idx="55"/>
</Inputs>
<Outputs>
	<Output idx="49" type="I1"/>
</Outputs>
<RecParents>
</RecParents>
</Node>

<Node idx="41"ASAP="6"BB="for.body7.us.us">
<OP>ADD</OP>
<Inputs>
	<Input idx="40"/>
	<Input idx="45"/>
</Inputs>
<Outputs>
	<Output idx="39" type="I1"/>
</Outputs>
<RecParents>
</RecParents>
</Node>

<Node idx="31"ASAP="6"BB="for.body7.us.us">
<OP>ADD</OP>
<Inputs>
	<Input idx="30"/>
	<Input idx="35"/>
</Inputs>
<Outputs>
	<Output idx="29" type="I1"/>
</Outputs>
<RecParents>
</RecParents>
</Node>

<Node idx="71"ASAP="6"BB="for.body7.us.us">
<OP>ADD</OP>
<Inputs>
	<Input idx="70"/>
	<Input idx="75"/>
</Inputs>
<Outputs>
	<Output idx="69" type="I1"/>
</Outputs>
<RecParents>
</RecParents>
</Node>

<Node idx="69"ASAP="7"BB="for.body7.us.us">
<OP>STORE</OP>
<Inputs>
	<Input idx="68"/>
	<Input idx="71"/>
</Inputs>
<Outputs>
</Outputs>
<RecParents>
	<RecParent idx="8"/>
	<RecParent idx="13"/>
	<RecParent idx="20"/>
	<RecParent idx="24"/>
	<RecParent idx="30"/>
	<RecParent idx="34"/>
	<RecParent idx="40"/>
	<RecParent idx="44"/>
	<RecParent idx="50"/>
	<RecParent idx="54"/>
	<RecParent idx="60"/>
	<RecParent idx="64"/>
</RecParents>
</Node>

<Node idx="39"ASAP="7"BB="for.body7.us.us">
<OP>STORE</OP>
<Inputs>
	<Input idx="38"/>
	<Input idx="41"/>
</Inputs>
<Outputs>
</Outputs>
<RecParents>
	<RecParent idx="8"/>
	<RecParent idx="13"/>
	<RecParent idx="20"/>
	<RecParent idx="24"/>
	<RecParent idx="30"/>
	<RecParent idx="34"/>
</RecParents>
</Node>

<Node idx="29"ASAP="7"BB="for.body7.us.us">
<OP>STORE</OP>
<Inputs>
	<Input idx="28"/>
	<Input idx="31"/>
</Inputs>
<Outputs>
</Outputs>
<RecParents>
	<RecParent idx="8"/>
	<RecParent idx="13"/>
	<RecParent idx="20"/>
	<RecParent idx="24"/>
</RecParents>
</Node>

<Node idx="7"ASAP="7"BB="for.body7.us.us">
<OP>STORE</OP>
<Inputs>
	<Input idx="6"/>
	<Input idx="9"/>
</Inputs>
<Outputs>
</Outputs>
<RecParents>
</RecParents>
</Node>

<Node idx="49"ASAP="7"BB="for.body7.us.us">
<OP>STORE</OP>
<Inputs>
	<Input idx="48"/>
	<Input idx="51"/>
</Inputs>
<Outputs>
</Outputs>
<RecParents>
	<RecParent idx="8"/>
	<RecParent idx="13"/>
	<RecParent idx="20"/>
	<RecParent idx="24"/>
	<RecParent idx="30"/>
	<RecParent idx="34"/>
	<RecParent idx="40"/>
	<RecParent idx="44"/>
</RecParents>
</Node>

<Node idx="59"ASAP="7"BB="for.body7.us.us">
<OP>STORE</OP>
<Inputs>
	<Input idx="58"/>
	<Input idx="61"/>
</Inputs>
<Outputs>
</Outputs>
<RecParents>
	<RecParent idx="8"/>
	<RecParent idx="13"/>
	<RecParent idx="20"/>
	<RecParent idx="24"/>
	<RecParent idx="30"/>
	<RecParent idx="34"/>
	<RecParent idx="40"/>
	<RecParent idx="44"/>
	<RecParent idx="50"/>
	<RecParent idx="54"/>
</RecParents>
</Node>

<Node idx="19"ASAP="7"BB="for.body7.us.us">
<OP>STORE</OP>
<Inputs>
	<Input idx="18"/>
	<Input idx="21"/>
</Inputs>
<Outputs>
</Outputs>
<RecParents>
	<RecParent idx="8"/>
	<RecParent idx="13"/>
</RecParents>
</Node>

</DFG>
